deci_adk/__init__.py
deci_adk/autonac.py
deci_adk/version.py
deci_adk-1.0.3.dist-info/WHEEL
deci_adk-1.0.3.dist-info/METADATA
deci_adk-1.0.3.dist-info/RECORD
